hublib/__init__.py
hublib/cmd/__init__.py
hublib/cmd/command.py
hublib/cmd/test/UnicodeTestλ.py
hublib/cmd/test/foo.py
hublib/cmd/test/test_command.py
hublib/cmd/test/testfoo.py
hublib/rappture/__init__.py
hublib/rappture/curve.py
hublib/rappture/hist.py
hublib/rappture/image.py
hublib/rappture/integer.py
hublib/rappture/loader.py
hublib/rappture/node.py
hublib/rappture/number.py
hublib/rappture/rappture.py
hublib/rappture/structure.py
hublib/rappture/tool.py
hublib/rappture/util.py
hublib/rappture/test/__init__.py
hublib/rappture/test/test_basic.py
hublib/rappture/test/test_boolean.py
hublib/rappture/test/test_choice.py
hublib/rappture/test/test_current.py
hublib/rappture/test/test_curve.py
hublib/rappture/test/test_integer.py
hublib/rappture/test/test_log.py
hublib/rappture/test/test_number.py
hublib/tool/__init__.py
hublib/tool/input_types.py
hublib/tool/rw.py
hublib/ui/__init__.py
hublib/ui/command.py
hublib/ui/download.py
hublib/ui/editor.py
hublib/ui/formvalue.py
hublib/ui/group.py
hublib/ui/hidecode.py
hublib/ui/listmanager.py
hublib/ui/modal.py
hublib/ui/numvalue.py
hublib/ui/pathselect.py
hublib/ui/submit.py
hublib/ui/upload.py
hublib/ui/uq.py
hublib/ui/test/__init__.py
hublib/ui/test/test_dropdown.py
hublib/ui/test/test_groups.py
hublib/ui/test/test_integer.py
hublib/ui/test/test_number.py
hublib/ui/test/test_radio.py
hublib/ui/test/test_string.py
hublib/ui/test/test_text.py
hublib/ui/test/test_toggle.py
hublib/uq/__init__.py
hublib/use/__init__.py
hublib/util/__init__.py
hublib-0.9.97.dist-info/DESCRIPTION.rst
hublib-0.9.97.dist-info/METADATA
hublib-0.9.97.dist-info/RECORD
hublib-0.9.97.dist-info/WHEEL
hublib-0.9.97.dist-info/metadata.json
hublib-0.9.97.dist-info/top_level.txt
