Metadata-Version: 2.0
Name: hublib
Version: 0.9.97
Summary: Python library for HUBzero Jupyter Notebooks
Home-page: https://github.com/hubzero/hublib
Author: Martin Hunt
Author-email: mmh@purdue.edu
License: MIT Software License
Platform: any
Classifier: Programming Language :: Python
Classifier: Development Status :: 3 - Alpha
Classifier: Intended Audience :: Developers
Classifier: License :: OSI Approved :: MIT License
Classifier: Operating System :: POSIX :: Linux
Classifier: Operating System :: MacOS :: MacOS X
Classifier: Topic :: Scientific/Engineering :: Information Analysis
Requires-Dist: filelock
Requires-Dist: ipywidgets (>=7.0)
Requires-Dist: joblib
Requires-Dist: pint
